setup.py
funniest/__init__.py
funniest/text.py
funniest_sravan.egg-info/PKG-INFO
funniest_sravan.egg-info/SOURCES.txt
funniest_sravan.egg-info/dependency_links.txt
funniest_sravan.egg-info/not-zip-safe
funniest_sravan.egg-info/requires.txt
funniest_sravan.egg-info/top_level.txt