Metadata-Version: 1.0
Name: funniest-sravan
Version: 0.1.2
Summary: The funniest joke in the world
Home-page: http://github.com/sravankorumilli/funniest
Author: Sravan
Author-email: sravan@example.com
License: MIT
Platform: UNKNOWN
